imio.news.core-1.2.16-py3.12-nspkg.pth
imio/news/core/__init__.py
imio/news/core/configure.zcml
imio/news/core/converters.py
imio/news/core/indexers.py
imio/news/core/indexers.zcml
imio/news/core/interfaces.py
imio/news/core/overrides.zcml
imio/news/core/permissions.zcml
imio/news/core/profiles.zcml
imio/news/core/setuphandlers.py
imio/news/core/subscribers.py
imio/news/core/subscribers.zcml
imio/news/core/testing.py
imio/news/core/utils.py
imio/news/core/vocabularies.py
imio/news/core/vocabularies.zcml
imio/news/core/browser/__init__.py
imio/news/core/browser/actions.py
imio/news/core/browser/configure.zcml
imio/news/core/browser/bring_news_into_news_folders/__init__.py
imio/news/core/browser/bring_news_into_news_folders/configure.zcml
imio/news/core/browser/bring_news_into_news_folders/news_folders.py
imio/news/core/browser/overrides/.gitkeep
imio/news/core/browser/static/.gitkeep
imio/news/core/contents/__init__.py
imio/news/core/contents/configure.zcml
imio/news/core/contents/entity/__init__.py
imio/news/core/contents/entity/configure.zcml
imio/news/core/contents/entity/content.py
imio/news/core/contents/folder/__init__.py
imio/news/core/contents/folder/configure.zcml
imio/news/core/contents/folder/content.py
imio/news/core/contents/newsfolder/__init__.py
imio/news/core/contents/newsfolder/configure.zcml
imio/news/core/contents/newsfolder/content.py
imio/news/core/contents/newsitem/__init__.py
imio/news/core/contents/newsitem/configure.zcml
imio/news/core/contents/newsitem/content.py
imio/news/core/contents/newsitem/serializer.py
imio/news/core/contents/newsitem/view.pt
imio/news/core/contents/newsitem/views.py
imio/news/core/faceted/config/news.xml
imio/news/core/profiles/default/browserlayer.xml
imio/news/core/profiles/default/catalog.xml
imio/news/core/profiles/default/contentrules.xml
imio/news/core/profiles/default/diff_tool.xml
imio/news/core/profiles/default/metadata.xml
imio/news/core/profiles/default/registry.xml
imio_news_core-1.2.16.dist-info/licenses/LICENSE.GPL
imio_news_core-1.2.16.dist-info/licenses/LICENSE.rst
imio_news_core-1.2.16.dist-info/METADATA
imio_news_core-1.2.16.dist-info/WHEEL
imio_news_core-1.2.16.dist-info/namespace_packages.txt
imio_news_core-1.2.16.dist-info/top_level.txt
imio_news_core-1.2.16.dist-info/RECORD
